CHANGES.rst
DESCRIPTION.rst
LICENSE
MANIFEST.in
README.md
setup.py
src/adc/class_lister.py
src/adc/core.py
src/adc/help.py
src/adc/registry.py
src/adc/api/__init__.py
src/adc/api/_classification.py
src/adc/api/_data.py
src/adc/api/_data_types.py
src/adc/api/_filter.py
src/adc/api/_generator.py
src/adc/api/_reader.py
src/adc/api/_speech.py
src/adc/api/_utils.py
src/adc/api/_writer.py
src/adc/filter/__init__.py
src/adc/filter/_base_audio_augmentation.py
src/adc/filter/_check_duplicate_filenames.py
src/adc/filter/_convert_to_mono.py
src/adc/filter/_convert_to_wav.py
src/adc/filter/_discard_by_name.py
src/adc/filter/_discard_negatives.py
src/adc/filter/_max_records.py
src/adc/filter/_metadata.py
src/adc/filter/_metadata_from_name.py
src/adc/filter/_metadata_to_placeholder.py
src/adc/filter/_passthrough.py
src/adc/filter/_pitch_shift.py
src/adc/filter/_pyfunc_filter.py
src/adc/filter/_randomize_records.py
src/adc/filter/_record_window.py
src/adc/filter/_rename.py
src/adc/filter/_resample.py
src/adc/filter/_sample.py
src/adc/filter/_set_placeholder.py
src/adc/filter/_split_records.py
src/adc/filter/_strip_annotations.py
src/adc/filter/_tee.py
src/adc/filter/_time_stretch.py
src/adc/filter/_trim_silence.py
src/adc/filter/classification/__init__.py
src/adc/filter/speech/__init__.py
src/adc/generator/__init__.py
src/adc/generator/_dirs.py
src/adc/generator/_list.py
src/adc/generator/_null.py
src/adc/generator/_range.py
src/adc/reader/__init__.py
src/adc/reader/_data.py
src/adc/reader/_multi.py
src/adc/reader/_poll_dir.py
src/adc/reader/_pyfunc.py
src/adc/reader/classification/__init__.py
src/adc/reader/classification/_adams.py
src/adc/reader/classification/_subdir.py
src/adc/reader/classification/_txt.py
src/adc/reader/speech/__init__.py
src/adc/reader/speech/_adams.py
src/adc/reader/speech/_commonvoice.py
src/adc/reader/speech/_festvox.py
src/adc/reader/speech/_hf_audiofolder.py
src/adc/reader/speech/_txt.py
src/adc/tool/__init__.py
src/adc/tool/convert.py
src/audio_dataset_converter.egg-info/PKG-INFO
src/audio_dataset_converter.egg-info/SOURCES.txt
src/audio_dataset_converter.egg-info/dependency_links.txt
src/audio_dataset_converter.egg-info/entry_points.txt
src/audio_dataset_converter.egg-info/requires.txt
src/audio_dataset_converter.egg-info/top_level.txt