Metadata-Version: 2.1
Name: audio-dataset-converter
Version: 0.0.3
Summary: Python3 library for converting between various audio dataset formats.
Home-page: https://github.com/waikato-llm/audio-dataset-converter
Author: Peter Reutemann
Author-email: fracpete@waikato.ac.nz
License: MIT License
Classifier: Development Status :: 4 - Beta
Classifier: License :: OSI Approved :: MIT License
Classifier: Topic :: Scientific/Engineering :: Artificial Intelligence
Classifier: Topic :: Multimedia :: Sound/Audio :: Conversion
License-File: LICENSE
